kl_mindbox_shapes_33/__init__.py
kl_mindbox_shapes_33/base.py
kl_mindbox_shapes_33/circle.py
kl_mindbox_shapes_33/core.py
kl_mindbox_shapes_33/triangle.py
kl_mindbox_shapes_33-1.1.1.dist-info/licenses/LICENCE
kl_mindbox_shapes_33-1.1.1.dist-info/METADATA
kl_mindbox_shapes_33-1.1.1.dist-info/WHEEL
kl_mindbox_shapes_33-1.1.1.dist-info/top_level.txt
kl_mindbox_shapes_33-1.1.1.dist-info/RECORD
